pdfmajor/__init__.py
pdfmajor/execptions.py
pdfmajor/BMPWriter/__init__.py
pdfmajor/converters/__init__.py
pdfmajor/converters/html.py
pdfmajor/converters/json.py
pdfmajor/converters/text.py
pdfmajor/converters/xml.py
pdfmajor/converters/yaml.py
pdfmajor/converters/writers/__init__.py
pdfmajor/converters/writers/html.py
pdfmajor/converters/writers/json.py
pdfmajor/converters/writers/xml.py
pdfmajor/converters/writers/yaml.py
pdfmajor/interpreter/PageInterpreter.py
pdfmajor/interpreter/__init__.py
pdfmajor/interpreter/commands/PDFCommands.py
pdfmajor/interpreter/commands/__init__.py
pdfmajor/interpreter/commands/commands.py
pdfmajor/interpreter/commands/utils.py
pdfmajor/interpreter/commands/state/Curves.py
pdfmajor/interpreter/commands/state/__init__.py
pdfmajor/interpreter/commands/state/PDFGraphicState/PDFColor.py
pdfmajor/interpreter/commands/state/PDFGraphicState/PDFColorSpace.py
pdfmajor/interpreter/commands/state/PDFGraphicState/__init__.py
pdfmajor/interpreter/commands/state/PDFItem/PDFImage.py
pdfmajor/interpreter/commands/state/PDFItem/PDFShape.py
pdfmajor/interpreter/commands/state/PDFItem/PDFText.py
pdfmajor/interpreter/commands/state/PDFItem/PDFXObject.py
pdfmajor/interpreter/commands/state/PDFItem/TextDecoder.py
pdfmajor/interpreter/commands/state/PDFItem/__init__.py
pdfmajor/interpreter/commands/state/PDFItem/_base.py
pdfmajor/interpreter/commands/state/PDFTextState/__init__.py
pdfmajor/interpreter/commands/state/PDFTextState/PDFFont/CFFFont.py
pdfmajor/interpreter/commands/state/PDFTextState/PDFFont/PDFFont.py
pdfmajor/interpreter/commands/state/PDFTextState/PDFFont/TrueTypeFont.py
pdfmajor/interpreter/commands/state/PDFTextState/PDFFont/Type1FontHeaderParser.py
pdfmajor/interpreter/commands/state/PDFTextState/PDFFont/__init__.py
pdfmajor/interpreter/commands/state/PDFTextState/PDFFont/fonts.py
pdfmajor/interpreter/commands/state/PDFTextState/PDFFont/util.py
pdfmajor/interpreter/commands/state/layout/LTChar.py
pdfmajor-1.3.13.dist-info/LICENSE
pdfmajor-1.3.13.dist-info/METADATA
pdfmajor-1.3.13.dist-info/WHEEL
pdfmajor-1.3.13.dist-info/top_level.txt
pdfmajor-1.3.13.dist-info/RECORD
