Metadata-Version: 2.1
Name: pdfmajor
Version: 1.3.13
Summary: PDF parser
Home-page: https://github.com/asosnovsky/pdfmajor
Author: Ariel Sosnovsky + Yusuke Shinyama + Philippe Guglielmetti
Author-email: ariel@sosnovsky.ca
License: MIT/X
Keywords: pdf parser,pdf converter,text mining
Platform: UNKNOWN
Classifier: Programming Language :: Python
Classifier: Programming Language :: Python :: 3.6
Classifier: Programming Language :: Python :: 3.7
Classifier: Development Status :: 5 - Production/Stable
Classifier: Environment :: Console
Classifier: Intended Audience :: Developers
Classifier: Intended Audience :: Science/Research
Classifier: License :: OSI Approved :: MIT License
Classifier: Topic :: Text Processing
Requires-Dist: pycryptodome (==3.8.2)
Requires-Dist: chardet (==3.0.4)
Requires-Dist: Pillow (>=6.2.0)
Provides-Extra: dev
Requires-Dist: tqdm (==4.32.1) ; extra == 'dev'
Requires-Dist: mkdocs (==1.0.4) ; extra == 'dev'
